odoo/addons/product_customerinfo_picking/README.rst
odoo/addons/product_customerinfo_picking/__init__.py
odoo/addons/product_customerinfo_picking/__manifest__.py
odoo/addons/product_customerinfo_picking/i18n/de.po
odoo/addons/product_customerinfo_picking/i18n/it.po
odoo/addons/product_customerinfo_picking/i18n/nl.po
odoo/addons/product_customerinfo_picking/i18n/nl_NL.po
odoo/addons/product_customerinfo_picking/i18n/product_customerinfo_picking.pot
odoo/addons/product_customerinfo_picking/i18n/product_supplierinfo_for_customer_picking.pot
odoo/addons/product_customerinfo_picking/i18n/pt_BR.po
odoo/addons/product_customerinfo_picking/models/__init__.py
odoo/addons/product_customerinfo_picking/models/stock_move.py
odoo/addons/product_customerinfo_picking/readme/CONTRIBUTORS.md
odoo/addons/product_customerinfo_picking/readme/DESCRIPTION.md
odoo/addons/product_customerinfo_picking/static/description/icon.png
odoo/addons/product_customerinfo_picking/static/description/index.html
odoo/addons/product_customerinfo_picking/tests/__init__.py
odoo/addons/product_customerinfo_picking/tests/test_product_customerinfo_picking.py
odoo/addons/product_customerinfo_picking/views/stock_picking_view.xml
odoo_addon_product_customerinfo_picking-18.0.1.0.0.6.dist-info/METADATA
odoo_addon_product_customerinfo_picking-18.0.1.0.0.6.dist-info/WHEEL
odoo_addon_product_customerinfo_picking-18.0.1.0.0.6.dist-info/top_level.txt
odoo_addon_product_customerinfo_picking-18.0.1.0.0.6.dist-info/RECORD
