Metadata-Version: 2.1
Name: odoo-addon-product_customerinfo_picking
Version: 18.0.1.0.0.6
Requires-Python: >=3.10
Requires-Dist: odoo-addon-product_customerinfo==18.0.*
Requires-Dist: odoo==18.0.*
Summary: This module makes the product customer code visible in the stock moves of a picking.
Home-page: https://github.com/OCA/stock-logistics-workflow
License: AGPL-3
Author: Agile Business Group, Odoo Community Association (OCA)
Author-email: support@odoo-community.org
Classifier: Programming Language :: Python
Classifier: Framework :: Odoo
Classifier: Framework :: Odoo :: 18.0
Classifier: License :: OSI Approved :: GNU Affero General Public License v3
